MANIFEST.in
README.rst
requirements.txt
setup.py
rubik_solver/Cubie.py
rubik_solver/CubieCube.py
rubik_solver/Enums.py
rubik_solver/Face.py
rubik_solver/FaceCube.py
rubik_solver/Move.py
rubik_solver/NaiveCube.py
rubik_solver/Printer.py
rubik_solver/__init__.py
rubik_solver/utils.py
rubik_solver.egg-info/PKG-INFO
rubik_solver.egg-info/SOURCES.txt
rubik_solver.egg-info/dependency_links.txt
rubik_solver.egg-info/entry_points.txt
rubik_solver.egg-info/requires.txt
rubik_solver.egg-info/top_level.txt
rubik_solver/CoordCube/__init__.py
rubik_solver/CoordCube/flip_move.csv
rubik_solver/CoordCube/fr_to_br_move.csv
rubik_solver/CoordCube/merge_ur_to_ul_and_ub_to_df_move.csv
rubik_solver/CoordCube/slice_flip_prun.csv
rubik_solver/CoordCube/slice_twist_prun.csv
rubik_solver/CoordCube/slice_ur_to_df_parity_prun.csv
rubik_solver/CoordCube/slice_urf_to_dlf_parity_prun.csv
rubik_solver/CoordCube/twist_move.csv
rubik_solver/CoordCube/ub_to_df_move.csv
rubik_solver/CoordCube/ur_to_df_move.csv
rubik_solver/CoordCube/ur_to_ul_move.csv
rubik_solver/CoordCube/urf_to_dlf_move.csv
rubik_solver/Solver/__init__.py
rubik_solver/Solver/Beginner/SecondLayerSolver.py
rubik_solver/Solver/Beginner/WhiteCrossSolver.py
rubik_solver/Solver/Beginner/WhiteFaceSolver.py
rubik_solver/Solver/Beginner/YellowCrossSolver.py
rubik_solver/Solver/Beginner/YellowFaceSolver.py
rubik_solver/Solver/Beginner/__init__.py
rubik_solver/Solver/CFOP/F2LSolver.py
rubik_solver/Solver/CFOP/OLLSolver.py
rubik_solver/Solver/CFOP/PLLSolver.py
rubik_solver/Solver/CFOP/__init__.py
rubik_solver/Solver/Kociemba/Search.py
rubik_solver/Solver/Kociemba/__init__.py