Metadata-Version: 1.1
Name: rubik-solver
Version: 0.1.5
Summary: Rubik solver algorithms
Home-page: https://github.com/Wiston999/python-rubik
Author: Victor Cabezas
Author-email: wiston666@gmail.com
License: UNKNOWN
Platform: UNKNOWN
Classifier: Development Status :: 3 - Alpha
Classifier: License :: OSI Approved :: MIT License
Classifier: Programming Language :: Python :: 2.7
Classifier: Programming Language :: Python :: 3.3
Classifier: Programming Language :: Python :: 3.4
Classifier: Programming Language :: Python :: 3.5
Classifier: Programming Language :: Python :: 3.6
